dokklib_db_extended/__init__.py
dokklib_db_extended/index.py
dokklib_db_extended/keys.py
dokklib_db_extended/op_args.py
dokklib_db_extended/py.typed
dokklib_db_extended/serializer.py
dokklib_db_extended/table.py
dokklib_db_extended/errors/__init__.py
dokklib_db_extended/errors/client.py
dokklib_db_extended/errors/exceptions.py
dokklib_db_extended/errors/transaction.py
dokklib_db_extended-0.1.7.dist-info/LICENSE
dokklib_db_extended-0.1.7.dist-info/METADATA
dokklib_db_extended-0.1.7.dist-info/NOTICE
dokklib_db_extended-0.1.7.dist-info/WHEEL
dokklib_db_extended-0.1.7.dist-info/top_level.txt
dokklib_db_extended-0.1.7.dist-info/RECORD
