Metadata-Version: 2.1
Name: dokklib-db-extended
Version: 0.1.7
Summary: DynamoDB Single Table Library
Home-page: https://github.com/cdominguezg/dokklib-db-extended
Author: Agost Biro, Cristian Dominguez
Author-email: agost+dokklib_db_extended@dokknet.com, crisdomgo@gmail.com
License: UNKNOWN
Download-URL: https://github.com/cdominguezg/dokklib-db-extended/archive/v0.1.7.tar.gz
Platform: UNKNOWN
Classifier: Development Status :: 4 - Beta
Classifier: Programming Language :: Python :: 3.8
Classifier: Programming Language :: Python :: 3.7
Classifier: Programming Language :: Python :: 3.6
Classifier: License :: OSI Approved :: Apache Software License
Classifier: Operating System :: OS Independent
Classifier: Topic :: Database
Requires-Python: >=3.6
Requires-Dist: boto3
Requires-Dist: typing-extensions (<4,>=3.7.2)
